bkr/__init__.py
bkr/cnvs.py
bkr/essentials/__init__.py
bkr/essentials/color.py
bkr/essentials/elm.py
bkr/essentials/utils.py
bkr/essentials/vector.py
bkr/illustrator/__init__.py
bkr/illustrator/image.py
bkr/illustrator/pathes.py
bkr/illustrator/shapes.py
bkr/illustrator/typography.py
bkr-0.0.1.dist-info/LICENSE.txt
bkr-0.0.1.dist-info/METADATA
bkr-0.0.1.dist-info/WHEEL
bkr-0.0.1.dist-info/top_level.txt
bkr-0.0.1.dist-info/RECORD
