Metadata-Version: 2.1
Name: bkr
Version: 0.0.1
Summary: SVG generator
Home-page: UNKNOWN
Author: Takaaki Yoneda
Author-email: 
License: MIT
Keywords: SVG
Platform: UNKNOWN
Classifier: Development Status :: 3 - Alpha
Classifier: Intended Audience :: Information Technology
Classifier: Operating System :: OS Independent
Classifier: License :: OSI Approved :: MIT License
Classifier: Programming Language :: Python :: 3
Requires-Python: >=3.6
Requires-Dist: numpy
Requires-Dist: pillow
